defer/__init__.py
defer/_version.py
defer/approximation.py
defer/bounded_space.py
defer/helpers.py
defer/sampling.py
defer/tree.py
defer/validation.py
defer/variables.py
defer/tree_construction/__init__.py
defer/tree_construction/algorithm.py
defer/tree_construction/divide_operator.py
defer/tree_construction/meta_direct.py
defer/tree_construction/utils.py
deference-0.1.1.dist-info/licenses/LICENSE
deference-0.1.1.dist-info/METADATA
deference-0.1.1.dist-info/WHEEL
deference-0.1.1.dist-info/top_level.txt
deference-0.1.1.dist-info/RECORD
