Metadata-Version: 2.4
Name: deference
Version: 0.1.1
Summary: DEnsity Function Estimation using Recursive partitioning
Author-email: Erik Bodin <mail@erikbodin.com>
License: MIT
Project-URL: Homepage, https://github.com/bodin-e/defer
Project-URL: Repository, https://github.com/bodin-e/defer
Project-URL: Documentation, https://github.com/bodin-e/defer#readme
Project-URL: Issues, https://github.com/bodin-e/defer/issues
Keywords: density estimation,bayesian inference,machine learning,statistics
Classifier: Development Status :: 3 - Alpha
Classifier: Intended Audience :: Science/Research
Classifier: License :: OSI Approved :: MIT License
Classifier: Operating System :: OS Independent
Classifier: Programming Language :: Python :: 3
Classifier: Programming Language :: Python :: 3.7
Classifier: Programming Language :: Python :: 3.8
Classifier: Programming Language :: Python :: 3.9
Classifier: Programming Language :: Python :: 3.10
Classifier: Programming Language :: Python :: 3.11
Classifier: Topic :: Scientific/Engineering :: Mathematics
Classifier: Topic :: Scientific/Engineering :: Physics
Requires-Python: >=3.7
License-File: LICENSE
Requires-Dist: numpy>=1.21.0
Requires-Dist: scipy>=1.7.0
Requires-Dist: scikit-spatial>=5.0.0
Requires-Dist: xxhash>=1.4.3
Requires-Dist: sobol-seq>=0.1.2
Provides-Extra: dev
Requires-Dist: pytest; extra == "dev"
Requires-Dist: pytest-cov; extra == "dev"
Requires-Dist: black; extra == "dev"
Requires-Dist: flake8; extra == "dev"
Requires-Dist: mypy; extra == "dev"
Provides-Extra: examples
Requires-Dist: bilby>=0.6.5; extra == "examples"
Requires-Dist: tensorflow>=2.1.0; extra == "examples"
Requires-Dist: tensorflow-probability>=0.8.0; extra == "examples"
Requires-Dist: corner>=2.0.1; extra == "examples"
Dynamic: license-file
